cheeta_jwt/__init__.py
cheeta_jwt/exception/__init__.py
cheeta_jwt/exception/validator_exception.py
cheeta_jwt/helper/__init__.py
cheeta_jwt/helper/jwt_helper.py
cheeta_jwt/helper/log_helper.py
cheeta_jwt/middleware/__init__.py
cheeta_jwt/middleware/jwt_middleware.py
cheeta_jwt/tests/__init__.py
cheeta_jwt/tests/app.py
cheeta_jwt/tests/conftest.py
cheeta_jwt/tests/jwthelper_test.py
cheeta_jwt/tests/test_validators.py
CheetaJWT-1.4.dist-info/LICENSE
CheetaJWT-1.4.dist-info/METADATA
CheetaJWT-1.4.dist-info/WHEEL
CheetaJWT-1.4.dist-info/top_level.txt
CheetaJWT-1.4.dist-info/RECORD
